LICENSE
README.md
setup.py
auro_joystick/__init__.py
auro_joystick/auro_joystick.py
auro_joystick.egg-info/PKG-INFO
auro_joystick.egg-info/SOURCES.txt
auro_joystick.egg-info/dependency_links.txt
auro_joystick.egg-info/not-zip-safe
auro_joystick.egg-info/requires.txt
auro_joystick.egg-info/top_level.txt