Metadata-Version: 2.1
Name: auro_joystick
Version: 1.0.2
Summary: Auro Joystick is a Python library designed for interfacing with joystick devices in robotics applications, offering robust support for ROS to facilitate easy integration.
Home-page: https://github.com/Auromix/auro_joystick
Author: Herman Ye
Author-email: hermanye233@icloud.com
License: Apache License 2.0
Keywords: auro_joystick
Classifier: Development Status :: 2 - Pre-Alpha
Classifier: Intended Audience :: Developers
Classifier: Natural Language :: English
Classifier: Programming Language :: Python :: 3
Classifier: Programming Language :: Python :: 3.8
Requires-Python: >=3.8
License-File: LICENSE
Requires-Dist: auro_utils==0.0.7
Requires-Dist: evdev
